dialogicai/__init__.py
dialogicai/core.py
dialogicai/utils.py
tests/__init__.py
tests/test_core.py
tests/test_utils.py
dialogic_ai-0.0.5.dist-info/LICENSE
dialogic_ai-0.0.5.dist-info/METADATA
dialogic_ai-0.0.5.dist-info/WHEEL
dialogic_ai-0.0.5.dist-info/top_level.txt
dialogic_ai-0.0.5.dist-info/RECORD
