Metadata-Version: 2.1
Name: dialogic-ai
Version: 0.0.5
Summary: A Python package designed to manage complex, threaded conversations with branching capabilities, much like version control systems manage code branches.
Home-page: https://github.com/endybits/dialogic-ai
Author: Endy Bermudez Rodriguez
Author-email: endyb.dev@gmail.com
License: MIT
Keywords: conversational AI,chat,chatbot,threaded conversations,AI,NLP,branching dialogues,dialogicai,dialogic-ai
Classifier: Programming Language :: Python :: 3
Classifier: License :: OSI Approved :: MIT License
Classifier: Operating System :: OS Independent
Requires-Python: >=3.8
License-File: LICENSE
Provides-Extra: dev
Requires-Dist: pytest>=8.3.2; extra == "dev"
Requires-Dist: black>=24.8.0; extra == "dev"
